<?xml version="1.0" encoding="UTF-8"?>
<xml>
    <entry type="car">
        <origin when="1911">Kwaishinsha Jidosha Kojo</origin>
        <meaning datsun="SonofDat"/>
        <name>Datsun 15 Phaeton</name>
        <built when="1936"/>
        <size>sedan</size>
        <tread type="front" quant="1038" unit="mm"/>
        <tread type="rear" quant="1049" unit="mm"/>
        <dimensions length="3187" width="1190" height="?" unit="mm"/>
        <seating>4</seating>
        <enginePower quant="12" unit="kW"/>
        <engineRPM>3600</engineRPM>
        <transmission quant="4" unit="cylinders"/>
        <curbWeight quant="" unit=""/>
        <wheelbase quant="2005" unit="mm"/>
        <suspension type="front">?</suspension>
        <suspension type="rear">?</suspension>
        <topSpeed quant="80" unit="km/hr"/>
        <image
            target="https://www.nissan-global.com/EN/HERITAGE/img/modelDetail/uploader/data/en/Web/1317194772214078845.jpg"/>
        <source target="https://www.nissan-global.com/EN/HERITAGE/datsun_15_phaeton.html"/>
    </entry>
</xml>

